{
  "1": {
    "name": "AMZ Hospital, Uttar Badda",
    "location": [23.7925, 90.4250],
    "address": "Uttar Badda, Dhaka 1212, Bangladesh",
    "phone": "+880-2-55012345",
    "emergency": true,
    "hours": "24/7"
  },
  "2": {
    "name": "Mirpur 12 Community Clinic",
    "location": [23.8290, 90.3654],
    "address": "Mirpur 12, Dhaka 1216, Bangladesh",
    "phone": "+880-2-55056789",
    "emergency": false,
    "hours": "8AM-6PM"
  },
  "3": {
    "name": "Banani Pet & Vet Care",
    "location": [23.7928, 90.4057],
    "address": "Road 11, Banani, Dhaka 1213, Bangladesh",
    "phone": "+880-2-55077889",
    "emergency": true,
    "hours": "24/7"
  },
  "4": {
    "name": "Dhanmondi Pet Clinic",
    "location": [23.7465, 90.3760],
    "address": "House 12, Road 4A, Dhanmondi, Dhaka 1209, Bangladesh",
    "phone": "+880-2-9123456",
    "emergency": false,
    "hours": "9AM-7PM"
  },
  "5": {
    "name": "Uttara Animal Hospital",
    "location": [23.8745, 90.3984],
    "address": "Sector 10, Uttara, Dhaka 1230, Bangladesh",
    "phone": "+880-2-58912345",
    "emergency": true,
    "hours": "24/7"
  }
}
